webinarJamBot/__init__.py
webinarJamBot/webinarJam.py
JAMBOT-0.0.2.dist-info/LICENSE
JAMBOT-0.0.2.dist-info/METADATA
JAMBOT-0.0.2.dist-info/WHEEL
JAMBOT-0.0.2.dist-info/entry_points.txt
JAMBOT-0.0.2.dist-info/top_level.txt
JAMBOT-0.0.2.dist-info/RECORD
